simplemathy/__init__.py
simplemathy-0.1.0.dist-info/METADATA
simplemathy-0.1.0.dist-info/WHEEL
simplemathy-0.1.0.dist-info/top_level.txt
simplemathy-0.1.0.dist-info/RECORD
