Metadata-Version: 2.4
Name: simplemathy
Version: 0.1.0
Summary: A tiny example package for learning PyPI publishing.
License: MIT
Project-URL: Homepage, https://pypi.org/project/simplemathy/
Requires-Python: >=3.8
